{
  "version": "2026-02",
  "fx": {
    "USD": 43.1,
    "EUR": 50.3
  },
  "hourly_cost": 459.3317550505049,
  "flange_diameters": {
    "15": {
      "150": 89,
      "300": 95,
      "400": 95.2,
      "600": 95.2,
      "900": 121,
      "1500": 121,
      "2500": 133.4
    },
    "20": {
      "150": 99,
      "300": 117,
      "400": 117.5,
      "600": 117.5,
      "900": 130,
      "1500": 130,
      "2500": 139.7
    },
    "25": {
      "150": 108,
      "300": 124,
      "400": 123.8,
      "600": 123.8,
      "900": 149.2,
      "1500": 149.2,
      "2500": 159
    },
    "32": {
      "150": 118,
      "300": 133,
      "400": 133.4,
      "600": 133.4,
      "900": 159,
      "1500": 159,
      "2500": 184.2
    },
    "40": {
      "150": 127,
      "300": 155,
      "400": 155,
      "600": 155,
      "900": 178,
      "1500": 178,
      "2500": 203
    },
    "50": {
      "150": 152,
      "300": 165,
      "400": 165,
      "600": 165,
      "900": 216,
      "1500": 216,
      "2500": 235
    },
    "65": {
      "150": 178,
      "300": 190,
      "400": 190,
      "600": 190,
      "900": 244,
      "1500": 244,
      "2500": 267
    },
    "80": {
      "150": 190,
      "300": 210,
      "400": 210,
      "600": 210,
      "900": 241,
      "1500": 267,
      "2500": 305
    },
    "100": {
      "150": 229,
      "300": 254,
      "400": 254,
      "600": 273,
      "900": 292,
      "1500": 311,
      "2500": 356
    },
    "125": {
      "150": 254,
      "300": 279,
      "400": 279,
      "600": 330,
      "900": 349,
      "1500": 375,
      "2500": 419
    },
    "150": {
      "150": 279,
      "300": 318,
      "400": 318,
      "600": 356,
      "900": 381,
      "1500": 394,
      "2500": 483
    },
    "200": {
      "150": 343,
      "300": 381,
      "400": 381,
      "600": 419,
      "900": 470,
      "1500": 483,
      "2500": 552
    },
    "250": {
      "150": 406,
      "300": 444,
      "400": 444,
      "600": 508,
      "900": 546,
      "1500": 584,
      "2500": 673
    },
    "300": {
      "150": 483,
      "300": 521,
      "400": 521,
      "600": 559,
      "900": 610,
      "1500": 673,
      "2500": 762
    },
    "350": {
      "150": 533,
      "300": 584,
      "400": 584,
      "600": 603,
      "900": 641,
      "1500": 749
    },
    "400": {
      "150": 597,
      "300": 648,
      "400": 648,
      "600": 686,
      "900": 705,
      "1500": 826
    },
    "450": {
      "150": 635,
      "300": 711,
      "400": 711,
      "600": 743,
      "900": 787,
      "1500": 914
    },
    "500": {
      "150": 698,
      "300": 775,
      "400": 775,
      "600": 813,
      "900": 857,
      "1500": 984
    },
    "550": {
      "150": 870,
      "300": 870
    },
    "600": {
      "150": 915,
      "300": 915,
      "400": 914,
      "600": 940,
      "900": 1041,
      "1500": 1168
    },
    "650": {},
    "700": {
      "150": 959.9999999999999,
      "300": 959.9999999999999
    },
    "750": {
      "150": 1010,
      "300": 1010
    },
    "800": {
      "150": 1085,
      "300": 1085
    },
    "850": {},
    "900": {
      "150": 1185,
      "300": 1185
    },
    "1000": {
      "150": 1319.9999999999998,
      "300": 1319.9999999999998
    }
  },
  "body_lengths": {
    "gate": {
      "15": {
        "150": {
          "L1": 140,
          "L1p": 162.4,
          "L2": 269
        },
        "300": {
          "L1": 151,
          "L1p": 179.4,
          "L2": 260
        },
        "600": {
          "L1": 163,
          "L1p": 204.6,
          "L2": 304
        },
        "2500": {
          "L1": 264,
          "L1p": 337.2,
          "L2": 450
        }
      },
      "20": {
        "150": {
          "L1": 140,
          "L1p": 165.4,
          "L2": 269
        },
        "300": {
          "L1": 165,
          "L1p": 196.4,
          "L2": 265
        },
        "600": {
          "L1": 190,
          "L1p": 234.2,
          "L2": 330
        },
        "2500": {
          "L1": 273,
          "L1p": 349.4,
          "L2": 475
        }
      },
      "25": {
        "150": {
          "L1": 140,
          "L1p": 168.4,
          "L2": 269
        },
        "300": {
          "L1": 178,
          "L1p": 212.4,
          "L2": 270
        },
        "600": {
          "L1": 216,
          "L1p": 263.8,
          "L2": 355
        },
        "900": {
          "L1": 254,
          "L1p": 324,
          "L2": 420
        },
        "1500": {
          "L1": 254,
          "L1p": 324,
          "L2": 460
        },
        "2500": {
          "L1": 308,
          "L1p": 391,
          "L2": 500
        }
      },
      "32": {
        "150": {
          "L1": 153,
          "L1p": 184.4,
          "L2": 280
        },
        "300": {
          "L1": 191,
          "L1p": 229,
          "L2": 320
        },
        "600": {
          "L1": 229,
          "L1p": 283,
          "L2": 370
        },
        "900": {
          "L1": 279,
          "L1p": 349,
          "L2": 430
        },
        "1500": {
          "L1": 279,
          "L1p": 349,
          "L2": 500
        },
        "2500": {
          "L1": 352,
          "L1p": 441,
          "L2": 570
        }
      },
      "40": {
        "150": {
          "L1": 178,
          "L1p": 212.8,
          "L2": 330
        },
        "300": {
          "L1": 203,
          "L1p": 244,
          "L2": 390
        },
        "600": {
          "L1": 241,
          "L1p": 299,
          "L2": 400
        },
        "900": {
          "L1": 305,
          "L1p": 381.4,
          "L2": 490
        },
        "1500": {
          "L1": 305,
          "L1p": 381.4,
          "L2": 570
        },
        "2500": {
          "L1": 387,
          "L1p": 489,
          "L2": 640
        }
      },
      "50": {
        "150": {
          "L1": 191,
          "L1p": 229,
          "L2": 409
        },
        "300": {
          "L1": 232,
          "L1p": 276.2,
          "L2": 424
        },
        "600": {
          "L1": 295,
          "L1p": 358.6,
          "L2": 458
        },
        "900": {
          "L1": 371,
          "L1p": 460,
          "L2": 620
        },
        "1500": {
          "L1": 371,
          "L1p": 460,
          "L2": 559
        },
        "2500": {
          "L1": 454,
          "L1p": 568.4,
          "L2": 700
        }
      },
      "65": {
        "150": {
          "L1": 203,
          "L1p": 247.2,
          "L2": 442
        },
        "300": {
          "L1": 257,
          "L1p": 307.8,
          "L2": 460
        },
        "600": {
          "L1": 333,
          "L1p": 402.6,
          "L2": 508
        },
        "900": {
          "L1": 422,
          "L1p": 517,
          "L2": 705
        },
        "1500": {
          "L1": 422,
          "L1p": 517,
          "L2": 673
        },
        "2500": {
          "L1": 514,
          "L1p": 641.2,
          "L2": 750
        }
      },
      "80": {
        "150": {
          "L1": 216,
          "L1p": 263.8,
          "L2": 508
        },
        "300": {
          "L1": 298,
          "L1p": 354.8,
          "L2": 535
        },
        "600": {
          "L1": 359,
          "L1p": 435.4,
          "L2": 570
        },
        "900": {
          "L1": 384,
          "L1p": 473,
          "L2": 695
        },
        "1500": {
          "L1": 473,
          "L1p": 581.4,
          "L2": 711
        },
        "2500": {
          "L1": 584,
          "L1p": 729.8,
          "L2": 887
        }
      },
      "100": {
        "150": {
          "L1": 242,
          "L1p": 289.8,
          "L2": 590
        },
        "300": {
          "L1": 321,
          "L1p": 384.4,
          "L2": 615
        },
        "600": {
          "L1": 435,
          "L1p": 518,
          "L2": 650
        },
        "900": {
          "L1": 460,
          "L1p": 561.8,
          "L2": 825
        },
        "1500": {
          "L1": 549,
          "L1p": 669.4,
          "L2": 838
        },
        "2500": {
          "L1": 683,
          "L1p": 848.2,
          "L2": 1079
        }
      },
      "125": {
        "150": {
          "L1": 267,
          "L1p": 314.8,
          "L2": 673
        },
        "300": {
          "L1": 397,
          "L1p": 466.6,
          "L2": 662
        },
        "600": {
          "L1": 511,
          "L1p": 612.6,
          "L2": 750
        },
        "900": {
          "L1": 562,
          "L1p": 676.4,
          "L2": 825
        },
        "1500": {
          "L1": 676,
          "L1p": 835.2,
          "L2": 838
        },
        "2500": {
          "L1": 807,
          "L1p": 1003.6,
          "L2": 1079
        }
      },
      "150": {
        "150": {
          "L1": 280,
          "L1p": 330.8,
          "L2": 767
        },
        "300": {
          "L1": 419,
          "L1p": 492.2,
          "L2": 795
        },
        "600": {
          "L1": 562,
          "L1p": 670.4,
          "L2": 872
        },
        "900": {
          "L1": 613,
          "L1p": 737,
          "L2": 1065
        },
        "1500": {
          "L1": 711,
          "L1p": 889,
          "L2": 1397
        },
        "2500": {
          "L1": 927,
          "L1p": 1155.8,
          "L2": 1370
        }
      },
      "200": {
        "150": {
          "L1": 305,
          "L1p": 361.8,
          "L2": 960
        },
        "300": {
          "L1": 435,
          "L1p": 517.2,
          "L2": 1012
        },
        "600": {
          "L1": 663,
          "L1p": 787,
          "L2": 1101
        },
        "900": {
          "L1": 740,
          "L1p": 879.8,
          "L2": 1320
        },
        "1500": {
          "L1": 842,
          "L1p": 1039,
          "L2": 1822
        },
        "2500": {
          "L1": 1038,
          "L1p": 1304.8,
          "L2": 1530
        }
      },
      "250": {
        "150": {
          "L1": 343,
          "L1p": 402.8,
          "L2": 1158
        },
        "300": {
          "L1": 473,
          "L1p": 568,
          "L2": 1231
        },
        "600": {
          "L1": 790,
          "L1p": 929.8,
          "L2": 1279
        },
        "900": {
          "L1": 841,
          "L1p": 993.4,
          "L2": 1540
        },
        "1500": {
          "L1": 1001,
          "L1p": 1229.8,
          "L2": 2051
        },
        "2500": {
          "L1": 1292,
          "L1p": 1635,
          "L2": 2045
        }
      },
      "300": {
        "150": {
          "L1": 369,
          "L1p": 432.4,
          "L2": 1378
        },
        "300": {
          "L1": 518,
          "L1p": 619.6,
          "L2": 1450
        },
        "600": {
          "L1": 841,
          "L1p": 986.8,
          "L2": 1468
        },
        "900": {
          "L1": 968,
          "L1p": 1139.2,
          "L2": 1840
        },
        "1500": {
          "L1": 1146,
          "L1p": 1406.8,
          "L2": 2134
        },
        "2500": {
          "L1": 1444,
          "L1p": 1825.2,
          "L2": 2145
        }
      },
      "350": {
        "150": {
          "L1": 394,
          "L1p": 463.6,
          "L2": 1543
        },
        "300": {
          "L1": 778,
          "L1p": 885.6,
          "L2": 1645
        },
        "600": {
          "L1": 892,
          "L1p": 1044.4,
          "L2": 1623
        },
        "900": {
          "L1": 1039,
          "L1p": 1223.6,
          "L2": 2025
        },
        "1500": {
          "L1": 1276,
          "L1p": 1555.6,
          "L2": 2267
        }
      },
      "400": {
        "150": {
          "L1": 419,
          "L1p": 492.2,
          "L2": 1738
        },
        "300": {
          "L1": 854,
          "L1p": 968.2,
          "L2": 1841
        },
        "600": {
          "L1": 994,
          "L1p": 1159.2,
          "L2": 1816
        },
        "900": {
          "L1": 1140,
          "L1p": 1330.6,
          "L2": 2170
        },
        "1500": {
          "L1": 1406,
          "L1p": 1710.8,
          "L2": 2420
        }
      },
      "450": {
        "150": {
          "L1": 445,
          "L1p": 524.2,
          "L2": 1959
        },
        "300": {
          "L1": 930,
          "L1p": 1050.4,
          "L2": 1943
        },
        "600": {
          "L1": 1095,
          "L1p": 1273,
          "L2": 2260
        },
        "900": {
          "L1": 1232,
          "L1p": 1448,
          "L2": 2232
        },
        "1500": {
          "L1": 1559,
          "L1p": 1896,
          "L2": 2600
        }
      },
      "500": {
        "150": {
          "L1": 470,
          "L1p": 555.2,
          "L2": 2214
        },
        "300": {
          "L1": 1010,
          "L1p": 1137,
          "L2": 2154
        },
        "600": {
          "L1": 1200,
          "L1p": 1390.6,
          "L2": 2705
        },
        "900": {
          "L1": 1334,
          "L1p": 1562.8,
          "L2": 2435
        },
        "1500": {
          "L1": 1686,
          "L1p": 2054.4,
          "L2": 2800
        }
      },
      "550": {
        "600": {
          "L1": 1305,
          "L1p": null,
          "L2": 2750
        }
      },
      "600": {
        "150": {
          "L1": 521,
          "L1p": 616,
          "L2": 2599
        },
        "300": {
          "L1": 1165,
          "L1p": 1304.6,
          "L2": 2553
        },
        "600": {
          "L1": 1407,
          "L1p": 1623,
          "L2": 2810
        },
        "900": {
          "L1": 1568,
          "L1p": 1860.2,
          "L2": 2865
        },
        "1500": {
          "L1": 1971,
          "L1p": 2390.2,
          "L2": 3250
        }
      },
      "650": {
        "300": {
          "L1": 1270,
          "L1p": 1375,
          "L2": 2750
        },
        "600": {
          "L1": 1461,
          "L1p": null,
          "L2": 2921
        }
      },
      "700": {
        "300": {
          "L1": 1371,
          "L1p": 1550,
          "L2": 3100
        },
        "600": {
          "L1": 1562,
          "L1p": null,
          "L2": 3136
        }
      },
      "750": {
        "300": {
          "L1": 1422,
          "L1p": 1660,
          "L2": 3320
        },
        "600": {
          "L1": 1664,
          "L1p": null,
          "L2": 3327
        }
      },
      "800": {
        "150": {
          "L1": 1755,
          "L1p": null,
          "L2": 3910
        },
        "300": {
          "L1": 1552,
          "L1p": 1780,
          "L2": 3560
        },
        "600": {
          "L1": 1794,
          "L1p": null,
          "L2": 3581
        }
      },
      "850": {
        "300": {
          "L1": 1654,
          "L1p": 1800,
          "L2": 3600
        },
        "600": {
          "L1": 1946,
          "L1p": null,
          "L2": 3750
        }
      },
      "900": {
        "300": {
          "L1": 1755,
          "L1p": 1955,
          "L2": 3910
        },
        "600": {
          "L1": 2099,
          "L1p": null,
          "L2": 4013
        }
      },
      "1000": {}
    },
    "globe": {
      "15": {
        "150": {
          "L1": 140,
          "L1p": 162.4,
          "L2": 269
        },
        "300": {
          "L1": 163,
          "L1p": 191.4,
          "L2": 260
        },
        "600": {
          "L1": 163,
          "L1p": 204.6,
          "L2": 304
        },
        "900": {
          "L1": 229,
          "L1p": 286.6,
          "L2": 300
        },
        "1500": {
          "L1": 216,
          "L1p": 273.6,
          "L2": 300
        },
        "2500": {
          "L1": 264,
          "L1p": 337.2,
          "L2": 300
        }
      },
      "20": {
        "150": {
          "L1": 140,
          "L1p": 165.4,
          "L2": 269
        },
        "300": {
          "L1": 191,
          "L1p": 222.4,
          "L2": 265
        },
        "600": {
          "L1": 190,
          "L1p": 234.2,
          "L2": 330
        },
        "900": {
          "L1": 229,
          "L1p": 292.8,
          "L2": 300
        },
        "1500": {
          "L1": 229,
          "L1p": 292.8,
          "L2": 300
        },
        "2500": {
          "L1": 273,
          "L1p": 349.4,
          "L2": 300
        }
      },
      "25": {
        "150": {
          "L1": 140,
          "L1p": 168.4,
          "L2": 269
        },
        "300": {
          "L1": 216,
          "L1p": 250.4,
          "L2": 270
        },
        "600": {
          "L1": 216,
          "L1p": 263.8,
          "L2": 355
        },
        "900": {
          "L1": 254,
          "L1p": 324,
          "L2": 300
        },
        "1500": {
          "L1": 254,
          "L1p": 324,
          "L2": 300
        },
        "2500": {
          "L1": 308,
          "L1p": 391,
          "L2": 300
        }
      },
      "32": {
        "150": {
          "L1": 153,
          "L1p": 184.4,
          "L2": 280
        },
        "300": {
          "L1": 229,
          "L1p": 267,
          "L2": 320
        },
        "600": {
          "L1": 229,
          "L1p": 283,
          "L2": 425
        },
        "900": {
          "L1": 279,
          "L1p": 349,
          "L2": 375
        },
        "1500": {
          "L1": 279,
          "L1p": 349,
          "L2": 375
        },
        "2500": {
          "L1": 352,
          "L1p": 441,
          "L2": 375
        }
      },
      "40": {
        "150": {
          "L1": 178,
          "L1p": 212.8,
          "L2": 330
        },
        "300": {
          "L1": 242,
          "L1p": 283,
          "L2": 390
        },
        "600": {
          "L1": 241,
          "L1p": 299,
          "L2": 400
        },
        "900": {
          "L1": 305,
          "L1p": 381.4,
          "L2": 450
        },
        "1500": {
          "L1": 305,
          "L1p": 381.4,
          "L2": 450
        },
        "2500": {
          "L1": 387,
          "L1p": 489,
          "L2": 450
        }
      },
      "50": {
        "150": {
          "L1": 216,
          "L1p": 254,
          "L2": 410
        },
        "300": {
          "L1": 283,
          "L1p": 327.2,
          "L2": 420
        },
        "600": {
          "L1": 295,
          "L1p": 358.6,
          "L2": 600
        },
        "900": {
          "L1": 371,
          "L1p": 460,
          "L2": 600
        },
        "1500": {
          "L1": 371,
          "L1p": 460,
          "L2": 546
        },
        "2500": {
          "L1": 454,
          "L1p": 568.4,
          "L2": 700
        }
      },
      "65": {
        "150": {
          "L1": 229,
          "L1p": 273.2,
          "L2": 432
        },
        "300": {
          "L1": 308,
          "L1p": 358.8,
          "L2": 435
        },
        "600": {
          "L1": 333,
          "L1p": 402.6,
          "L2": 660
        },
        "900": {
          "L1": 422,
          "L1p": 517,
          "L2": 660
        },
        "1500": {
          "L1": 422,
          "L1p": 517,
          "L2": 589
        },
        "2500": {
          "L1": 514,
          "L1p": 641.2,
          "L2": 750
        }
      },
      "80": {
        "150": {
          "L1": 254,
          "L1p": 301.8,
          "L2": 450
        },
        "300": {
          "L1": 334,
          "L1p": 390.8,
          "L2": 450
        },
        "600": {
          "L1": 359,
          "L1p": 435.4,
          "L2": 665
        },
        "900": {
          "L1": 384,
          "L1p": 473,
          "L2": 665
        },
        "1500": {
          "L1": 473,
          "L1p": 581.4,
          "L2": 711
        },
        "2500": {
          "L1": 584,
          "L1p": 729.8,
          "L2": 887
        }
      },
      "100": {
        "150": {
          "L1": 305,
          "L1p": 352.8,
          "L2": 500
        },
        "300": {
          "L1": 372,
          "L1p": 435.4,
          "L2": 520
        },
        "600": {
          "L1": 435,
          "L1p": 518,
          "L2": 800
        },
        "900": {
          "L1": 460,
          "L1p": 561.8,
          "L2": 800
        },
        "1500": {
          "L1": 549,
          "L1p": 669.4,
          "L2": 718
        },
        "2500": {
          "L1": 683,
          "L1p": 848.2,
          "L2": 1079
        }
      },
      "125": {
        "150": {
          "L1": 369,
          "L1p": 416.8,
          "L2": 538
        },
        "300": {
          "L1": 416,
          "L1p": 485.6,
          "L2": 620
        },
        "600": {
          "L1": 511,
          "L1p": 612.6,
          "L2": 1015
        },
        "900": {
          "L1": 562,
          "L1p": 676.4,
          "L2": 825
        },
        "1500": {
          "L1": 676,
          "L1p": 835.2,
          "L2": 838
        },
        "2500": {
          "L1": 807,
          "L1p": 1003.6,
          "L2": 1079
        }
      },
      "150": {
        "150": {
          "L1": 419,
          "L1p": 469.8,
          "L2": 550
        },
        "300": {
          "L1": 460,
          "L1p": 533.2,
          "L2": 650
        },
        "600": {
          "L1": 562,
          "L1p": 670.4,
          "L2": 1145
        },
        "900": {
          "L1": 613,
          "L1p": 737,
          "L2": 1015
        },
        "1500": {
          "L1": 711,
          "L1p": 889,
          "L2": 890
        },
        "2500": {
          "L1": 927,
          "L1p": 1155.8,
          "L2": 1370
        }
      },
      "200": {
        "150": {
          "L1": 508,
          "L1p": 564.8,
          "L2": 620
        },
        "300": {
          "L1": 575,
          "L1p": 657.2,
          "L2": 800
        },
        "600": {
          "L1": 663,
          "L1p": 787,
          "L2": 1278
        },
        "900": {
          "L1": 740,
          "L1p": 879.8,
          "L2": 1145
        },
        "1500": {
          "L1": 842,
          "L1p": 1039,
          "L2": 1240
        },
        "2500": {
          "L1": 1038,
          "L1p": 1304.8,
          "L2": 1530
        }
      },
      "250": {
        "150": {
          "L1": 635,
          "L1p": 694.8,
          "L2": 762
        },
        "300": {
          "L1": 638,
          "L1p": 733,
          "L2": 1040
        },
        "600": {
          "L1": 790,
          "L1p": 929.8,
          "L2": 1411
        },
        "900": {
          "L1": 841,
          "L1p": 993.4,
          "L2": 1278
        },
        "1500": {
          "L1": 1001,
          "L1p": 1229.8,
          "L2": 1651
        },
        "2500": {
          "L1": 1292,
          "L1p": 1635,
          "L2": 2045
        }
      },
      "300": {
        "150": {
          "L1": 711,
          "L1p": 774.4,
          "L2": 860
        },
        "300": {
          "L1": 727,
          "L1p": 828.6,
          "L2": 1140
        },
        "600": {
          "L1": 841,
          "L1p": 986.8,
          "L2": 1468
        },
        "900": {
          "L1": 968,
          "L1p": 1139.2,
          "L2": 1411
        },
        "1500": {
          "L1": 1146,
          "L1p": 1406.8,
          "L2": 1870
        },
        "2500": {
          "L1": 1444,
          "L1p": 1825.2,
          "L2": 2145
        }
      },
      "350": {
        "150": {
          "L1": 800,
          "L1p": 869.6,
          "L2": 1442
        },
        "900": {
          "L1": 1039,
          "L1p": 1223.6,
          "L2": 1700
        },
        "1500": {
          "L1": 1276,
          "L1p": 1555.6,
          "L2": 2267
        }
      },
      "400": {
        "150": {
          "L1": 927,
          "L1p": 1000.2,
          "L2": 1625
        }
      },
      "450": {},
      "500": {},
      "550": {},
      "600": {},
      "650": {},
      "700": {},
      "750": {},
      "800": {},
      "850": {},
      "900": {},
      "1000": {}
    },
    "butterfly": {
      "15": {
        "150": {
          "L1": 108,
          "L1p": 130.4,
          "L2": 95
        },
        "300": {
          "L1": 229,
          "L1p": 257.4,
          "L2": 140
        },
        "600": {
          "L1": 216,
          "L1p": 257.6,
          "L2": 140
        }
      },
      "20": {
        "150": {
          "L1": 117,
          "L1p": 142.4,
          "L2": 95
        },
        "300": {
          "L1": 229,
          "L1p": 260.4,
          "L2": 140
        },
        "600": {
          "L1": 216,
          "L1p": 260.2,
          "L2": 140
        }
      },
      "25": {
        "150": {
          "L1": 140,
          "L1p": 168.4,
          "L2": 110
        },
        "300": {
          "L1": 229,
          "L1p": 263.4,
          "L2": 140
        },
        "600": {
          "L1": 216,
          "L1p": 263.8,
          "L2": 140
        },
        "1500": {
          "L1": 254,
          "L1p": 324,
          "L2": 170
        },
        "2500": {
          "L1": 308,
          "L1p": 391,
          "L2": 160
        }
      },
      "32": {
        "150": {
          "L1": 153,
          "L1p": 184.4,
          "L2": 122
        },
        "300": {
          "L1": 242,
          "L1p": 280,
          "L2": 150
        },
        "600": {
          "L1": 229,
          "L1p": 283,
          "L2": 160
        },
        "900": {
          "L1": 279,
          "L1p": 349,
          "L2": 190
        },
        "1500": {
          "L1": 279,
          "L1p": 349,
          "L2": 200
        },
        "2500": {
          "L1": 352,
          "L1p": 441,
          "L2": 180
        }
      },
      "40": {
        "150": {
          "L1": 178,
          "L1p": 212.8,
          "L2": 140
        },
        "300": {
          "L1": 254,
          "L1p": 295,
          "L2": 155
        },
        "600": {
          "L1": 241,
          "L1p": 299,
          "L2": 180
        },
        "900": {
          "L1": 305,
          "L1p": 381.4,
          "L2": 220
        },
        "1500": {
          "L1": 305,
          "L1p": 381.4,
          "L2": 250
        },
        "2500": {
          "L1": 387,
          "L1p": 489,
          "L2": 200
        }
      },
      "50": {
        "150": {
          "L1": 216,
          "L1p": 254,
          "L2": 165
        },
        "300": {
          "L1": 283,
          "L1p": 327.2,
          "L2": 178
        },
        "600": {
          "L1": 295,
          "L1p": 358.6,
          "L2": 187
        },
        "900": {
          "L1": 371,
          "L1p": 460,
          "L2": 250
        },
        "1500": {
          "L1": 371,
          "L1p": 460,
          "L2": 310
        },
        "2500": {
          "L1": 454,
          "L1p": 568.4,
          "L2": 240
        }
      },
      "65": {
        "150": {
          "L1": 229,
          "L1p": 273.2,
          "L2": 178
        },
        "300": {
          "L1": 308,
          "L1p": 358.8,
          "L2": 191
        },
        "600": {
          "L1": 333,
          "L1p": 402.6,
          "L2": 216
        },
        "900": {
          "L1": 422,
          "L1p": 517,
          "L2": 270
        },
        "1500": {
          "L1": 422,
          "L1p": 517,
          "L2": 310
        },
        "2500": {
          "L1": 514,
          "L1p": 641.2,
          "L2": 290
        }
      },
      "80": {
        "150": {
          "L1": 254,
          "L1p": 301.8,
          "L2": 186
        },
        "300": {
          "L1": 334,
          "L1p": 390.8,
          "L2": 211
        },
        "600": {
          "L1": 359,
          "L1p": 435.4,
          "L2": 278
        },
        "900": {
          "L1": 384,
          "L1p": 473,
          "L2": 230
        },
        "1500": {
          "L1": 473,
          "L1p": 581.4,
          "L2": 330
        },
        "2500": {
          "L1": 584,
          "L1p": 729.8,
          "L2": 340
        }
      },
      "100": {
        "150": {
          "L1": 305,
          "L1p": 352.8,
          "L2": 217
        },
        "300": {
          "L1": 372,
          "L1p": 435.4,
          "L2": 246
        },
        "600": {
          "L1": 435,
          "L1p": 518,
          "L2": 316
        },
        "900": {
          "L1": 460,
          "L1p": 561.8,
          "L2": 310
        },
        "1500": {
          "L1": 549,
          "L1p": 669.4,
          "L2": 355
        },
        "2500": {
          "L1": 683,
          "L1p": 848.2,
          "L2": 390
        }
      },
      "125": {
        "150": {
          "L1": 343,
          "L1p": 390.8,
          "L2": 230
        },
        "300": {
          "L1": 416,
          "L1p": 485.6,
          "L2": 305
        },
        "600": {
          "L1": 511,
          "L1p": 612.6,
          "L2": 360
        },
        "900": {
          "L1": 562,
          "L1p": 676.4,
          "L2": 340
        },
        "1500": {
          "L1": 676,
          "L1p": 835.2,
          "L2": 375
        },
        "2500": {
          "L1": 807,
          "L1p": 1003.6,
          "L2": 440
        }
      },
      "150": {
        "150": {
          "L1": 369,
          "L1p": 419.8,
          "L2": 266
        },
        "300": {
          "L1": 460,
          "L1p": 533.2,
          "L2": 318
        },
        "600": {
          "L1": 562,
          "L1p": 670.4,
          "L2": 400
        },
        "900": {
          "L1": 613,
          "L1p": 737,
          "L2": 360
        },
        "1500": {
          "L1": 711,
          "L1p": 889,
          "L2": 400
        },
        "2500": {
          "L1": 927,
          "L1p": 1155.8,
          "L2": 500
        }
      },
      "200": {
        "150": {
          "L1": 508,
          "L1p": 564.8,
          "L2": 318
        },
        "300": {
          "L1": 549,
          "L1p": 631.2,
          "L2": 356
        },
        "600": {
          "L1": 663,
          "L1p": 787,
          "L2": 432
        },
        "900": {
          "L1": 740,
          "L1p": 879.8,
          "L2": 430
        },
        "1500": {
          "L1": 842,
          "L1p": 1039,
          "L2": 530
        },
        "2500": {
          "L1": 1038,
          "L1p": 1304.8,
          "L2": 630
        }
      },
      "250": {
        "150": {
          "L1": 635,
          "L1p": 694.8,
          "L2": 368
        },
        "300": {
          "L1": 638,
          "L1p": 733,
          "L2": 394
        },
        "600": {
          "L1": 790,
          "L1p": 929.8,
          "L2": 483
        },
        "900": {
          "L1": 841,
          "L1p": 993.4,
          "L2": 480
        },
        "1500": {
          "L1": 1001,
          "L1p": 1229.8,
          "L2": 560
        },
        "2500": {
          "L1": 1292,
          "L1p": 1635,
          "L2": 760
        }
      },
      "300": {
        "150": {
          "L1": 711,
          "L1p": 774.4,
          "L2": 406
        },
        "300": {
          "L1": 727,
          "L1p": 828.6,
          "L2": 482
        },
        "600": {
          "L1": 841,
          "L1p": 986.8,
          "L2": 508
        },
        "900": {
          "L1": 968,
          "L1p": 1139.2,
          "L2": 560
        },
        "1500": {
          "L1": 1146,
          "L1p": 1406.8,
          "L2": 650
        },
        "2500": {
          "L1": 1444,
          "L1p": 1825.2,
          "L2": 900
        }
      },
      "350": {
        "150": {
          "L1": 800,
          "L1p": 869.6,
          "L2": 432
        },
        "300": {
          "L1": 854,
          "L1p": 961.6,
          "L2": 533
        },
        "600": {
          "L1": 892,
          "L1p": 1044.4,
          "L2": 572
        },
        "900": {
          "L1": 1039,
          "L1p": 1223.6,
          "L2": 629
        },
        "1500": {
          "L1": 1276,
          "L1p": 1555.6,
          "L2": 785
        }
      },
      "400": {
        "150": {
          "L1": 877,
          "L1p": 950.2,
          "L2": 483
        },
        "300": {
          "L1": 880,
          "L1p": 994.2,
          "L2": 584
        },
        "600": {
          "L1": 994,
          "L1p": 1159.2,
          "L2": 660
        },
        "900": {
          "L1": 1140,
          "L1p": 1330.6,
          "L2": 700
        },
        "1500": {
          "L1": 1406,
          "L1p": 1710.8,
          "L2": 930
        }
      },
      "450": {
        "150": {
          "L1": 991,
          "L1p": 1070.2,
          "L2": 600
        },
        "300": {
          "L1": 994,
          "L1p": 1114.4,
          "L2": 590
        },
        "600": {
          "L1": 1095,
          "L1p": 1273,
          "L2": 730
        },
        "900": {
          "L1": 1232,
          "L1p": 1448,
          "L2": 800
        },
        "1500": {
          "L1": 1559,
          "L1p": 1896,
          "L2": 800
        }
      },
      "500": {
        "150": {
          "L1": 991,
          "L1p": 1076.2,
          "L2": 660
        },
        "300": {
          "L1": 1035,
          "L1p": 1162,
          "L2": 614
        },
        "600": {
          "L1": 1200,
          "L1p": 1390.6,
          "L2": 800
        },
        "900": {
          "L1": 1334,
          "L1p": 1562.8,
          "L2": 850
        },
        "1500": {
          "L1": 1686,
          "L1p": 2054.4,
          "L2": 870
        }
      },
      "550": {
        "150": {
          "L1": 1080,
          "L1p": "#VALUE!",
          "L2": 700
        },
        "300": {
          "L1": 1140,
          "L1p": "#VALUE!",
          "L2": 655
        },
        "600": {
          "L1": 1305,
          "L1p": "#VALUE!",
          "L2": 820
        }
      },
      "600": {
        "150": {
          "L1": 1308,
          "L1p": 1403,
          "L2": 740
        },
        "300": {
          "L1": 1368,
          "L1p": 1507.6,
          "L2": 720
        },
        "600": {
          "L1": 1407,
          "L1p": 1623,
          "L2": 900
        },
        "900": {
          "L1": 1568,
          "L1p": 1860.2,
          "L2": 950
        },
        "1500": {
          "L1": 1971,
          "L1p": 2390.2,
          "L2": 1000
        }
      },
      "650": {
        "150": {
          "L1": 1295,
          "L1p": "#VALUE!",
          "L2": 820
        },
        "300": {
          "L1": 1371,
          "L1p": "#VALUE!",
          "L2": 770
        },
        "600": {
          "L1": 1448,
          "L1p": "#VALUE!",
          "L2": 950
        }
      },
      "700": {
        "150": {
          "L1": 1448,
          "L1p": "#VALUE!",
          "L2": 900
        },
        "300": {
          "L1": 1524,
          "L1p": "#VALUE!",
          "L2": 830
        },
        "600": {
          "L1": 1600,
          "L1p": "#VALUE!",
          "L2": 1000
        }
      },
      "750": {
        "150": {
          "L1": 1524,
          "L1p": "#VALUE!",
          "L2": 980
        },
        "300": {
          "L1": 1619,
          "L1p": "#VALUE!",
          "L2": 860
        },
        "600": {
          "L1": 1651,
          "L1p": "#VALUE!",
          "L2": 1050
        }
      },
      "800": {},
      "850": {},
      "900": {
        "150": {
          "L1": 1956,
          "L1p": "#VALUE!",
          "L2": 1035
        },
        "300": {
          "L1": 2111,
          "L1p": "#VALUE!",
          "L2": 1060
        },
        "600": {
          "L1": 2083,
          "L1p": "#VALUE!",
          "L2": 1200
        }
      },
      "1000": {}
    }
  },
  "agraf_pul": {
    "1": {
      "a": 0,
      "p": 0
    },
    "1.25": {
      "a": 0,
      "p": 0
    },
    "1.5": {
      "a": 0,
      "p": 0
    },
    "2": {
      "a": 0,
      "p": 0
    },
    "2.5": {
      "a": 0,
      "p": 0
    },
    "3": {
      "a": 0,
      "p": 0
    },
    "4": {
      "a": 4,
      "p": 2
    },
    "5": {
      "a": 6,
      "p": 2
    },
    "6": {
      "a": 6,
      "p": 2
    },
    "8": {
      "a": 6,
      "p": 4
    },
    "10": {
      "a": 6,
      "p": 4
    },
    "12": {
      "a": 6,
      "p": 4
    },
    "14": {
      "a": 8,
      "p": 6
    },
    "16": {
      "a": 8,
      "p": 6
    },
    "18": {
      "a": 8,
      "p": 6
    },
    "20": {
      "a": 8,
      "p": 8
    },
    "22": {
      "a": 10,
      "p": 8
    },
    "24": {
      "a": 10,
      "p": 8
    },
    "28": {
      "a": 10,
      "p": 10
    },
    "30": {
      "a": 10,
      "p": 10
    },
    "32": {
      "a": 12,
      "p": 12
    },
    "36": {
      "a": 12,
      "p": 14
    },
    "40": {
      "a": 14,
      "p": 16
    },
    "64": {
      "a": 14,
      "p": 20
    },
    "0.75": {
      "a": 0,
      "p": 0
    },
    "0.5": {
      "a": 0,
      "p": 0
    }
  },
  "defaults": {
    "overhead_pct": 0.15,
    "sales_multiplier": 2.5,
    "prefix": "INSJACK",
    "difficulty": 1.2,
    "overlap_left": 0.8,
    "overlap_right": 1.0,
    "overlap_flange": 0.5,
    "overlap_width": 0.8,
    "insulation_waste_pct": 0.03,
    "padding_mm": 60
  },
  "dn_list": [
    15,
    20,
    25,
    32,
    40,
    50,
    65,
    80,
    100,
    125,
    150,
    200,
    250,
    300,
    350,
    400,
    450,
    500,
    550,
    600,
    650,
    700,
    750,
    800,
    850,
    900,
    1000
  ],
  "class_list": [
    150,
    300,
    400,
    600,
    900,
    1500,
    2500
  ],
  "dn_to_inch": {
    "15": 0.5,
    "20": 0.75,
    "25": 1,
    "32": 1.25,
    "40": 1.5,
    "50": 2,
    "65": 2.5,
    "80": 3,
    "100": 4,
    "125": 5,
    "150": 6,
    "200": 8,
    "250": 10,
    "300": 12,
    "350": 14,
    "400": 16,
    "450": 18,
    "500": 20,
    "550": 22,
    "600": 24,
    "650": 26,
    "700": 28,
    "750": 30,
    "800": 32,
    "850": 34,
    "900": 36,
    "1000": 40
  }
}